abasepyplatforms.cpython-311-i386-linux-musl.so
abasepyplatforms-0.0.1.dist-info/METADATA
abasepyplatforms-0.0.1.dist-info/LICENSE
abasepyplatforms-0.0.1.dist-info/WHEEL
abasepyplatforms-0.0.1.dist-info/RECORD
abasepyplatforms-0.0.1.dist-info/top_level.txt
